NOTICE
gen3config/__init__.py
gen3config/config.py
gen3config/errors.py
gen3config-2.0.0.dist-info/LICENSE
gen3config-2.0.0.dist-info/METADATA
gen3config-2.0.0.dist-info/NOTICE
gen3config-2.0.0.dist-info/WHEEL
gen3config-2.0.0.dist-info/RECORD
