Metadata-Version: 2.1
Name: gen3config
Version: 2.0.0
Summary: Gen3 Configuration Library
Home-page: https://github.com/uc-cdis/gen3config
License: Apache-2.0
Author: CTDS UChicago
Author-email: cdis@uchicago.edu
Requires-Python: >=3.9,<4.0
Classifier: License :: OSI Approved :: Apache Software License
Classifier: Programming Language :: Python :: 3
Classifier: Programming Language :: Python :: 3.9
Classifier: Programming Language :: Python :: 3.10
Classifier: Programming Language :: Python :: 3.11
Classifier: Programming Language :: Python :: 3.12
Classifier: Programming Language :: Python :: 3.13
Requires-Dist: cdiserrors
Requires-Dist: cdislogging
Requires-Dist: jinja2
Requires-Dist: pyyaml
Requires-Dist: six
Project-URL: Repository, https://github.com/uc-cdis/gen3config
